markupy/__init__.py
markupy/attributes.py
markupy/elements.py
markupy/exceptions.py
markupy/py.typed
markupy/_private/attributes/__init__.py
markupy/_private/attributes/attribute.py
markupy/_private/attributes/handlers.py
markupy/_private/attributes/html.py
markupy/_private/attributes/store.py
markupy/_private/html_to_markupy/__init__.py
markupy/_private/html_to_markupy/cli.py
markupy/_private/html_to_markupy/parser.py
markupy/_private/views/__init__.py
markupy/_private/views/component.py
markupy/_private/views/element.py
markupy/_private/views/fragment.py
markupy/_private/views/view.py
markupy-2.5.0.dist-info/entry_points.txt
markupy-2.5.0.dist-info/licenses/LICENSE
markupy-2.5.0.dist-info/WHEEL
markupy-2.5.0.dist-info/METADATA
markupy-2.5.0.dist-info/RECORD
