Metadata-Version: 2.4
Name: markupy
Version: 2.5.0
Summary: markupy - HTML in Python
Author-email: witiz <markupy@witiz.com>
Requires-Python: >=3.10
Classifier: Programming Language :: Python :: 3
Classifier: License :: OSI Approved :: MIT License
Classifier: Intended Audience :: Developers
Classifier: Development Status :: 5 - Production/Stable
Classifier: Topic :: Text Processing :: Markup :: HTML
Classifier: Operating System :: OS Independent
Classifier: Typing :: Typed
License-File: LICENSE
Requires-Dist: markupsafe>=2.0.0
Requires-Dist: typing-extensions>=4.12.2
Project-URL: Homepage, https://markupy.witiz.com
Project-URL: Issues, https://github.com/witiz/markupy/issues
Project-URL: Repository, https://github.com/witiz/markupy
Project-URL: html2markupy, https://html2markupy.witiz.com
